page/__init__.py
page/page/__init__.py
page/page/pg.py
page.page-0.0.1.dist-info/LICENSE.txt
page.page-0.0.1.dist-info/METADATA
page.page-0.0.1.dist-info/WHEEL
page.page-0.0.1.dist-info/top_level.txt
page.page-0.0.1.dist-info/RECORD
