Metadata-Version: 2.1
Name: page.page
Version: 0.0.1
Summary: desc.
Home-page: 
Author: a
Classifier: Programming Language :: Python :: 3
License-File: LICENSE.txt
